MANIFEST.in
README.rst
httpie_django_auth.py
setup.cfg
setup.py
httpie_django_auth.egg-info/PKG-INFO
httpie_django_auth.egg-info/SOURCES.txt
httpie_django_auth.egg-info/dependency_links.txt
httpie_django_auth.egg-info/entry_points.txt
httpie_django_auth.egg-info/requires.txt
httpie_django_auth.egg-info/top_level.txt