Metadata-Version: 1.1
Name: httpie-django-auth
Version: 0.1.1
Summary: django Auth plugin for HTTPie.
Home-page: https://github.com/chillaranand/httpie-django-auth
Author: Chillar Anand
Author-email: anand21nanda@gmail.com
License: UNKNOWN
Download-URL: https://github.com/chillaranand/httpie-django-auth
Platform: UNKNOWN
Classifier: Development Status :: 5 - Production/Stable
Classifier: Programming Language :: Python
Classifier: Intended Audience :: Developers
Classifier: Environment :: Plugins
Classifier: License :: OSI Approved :: MIT License
Classifier: Topic :: Internet :: WWW/HTTP
Classifier: Topic :: Utilities
